pytest_runtime_yoyo/__init__.py
pytest_runtime_yoyo/plugin.py
pytest_runtime_yoyo-1.0.1.dist-info/METADATA
pytest_runtime_yoyo-1.0.1.dist-info/WHEEL
pytest_runtime_yoyo-1.0.1.dist-info/entry_points.txt
pytest_runtime_yoyo-1.0.1.dist-info/top_level.txt
pytest_runtime_yoyo-1.0.1.dist-info/RECORD
