Metadata-Version: 2.1
Name: pytest-runtime-yoyo
Version: 1.0.1
Summary: run case mark timeout
Home-page: https://gitee.com/yoyoketang/pytest-runtime-yoyo
Author: 上海-悠悠
Author-email: 283340479@qq.com
License: proprietary
Keywords: pytest,py.test,pytest-runtime,pytest-runtime-yoyo
Classifier: Framework :: Pytest
Classifier: Programming Language :: Python
Classifier: Topic :: Software Development :: Testing
Classifier: Programming Language :: Python :: 3.8
Requires-Python: >=3.8
Requires-Dist: pytest (>=7.2.0)
